llamaapi/__init__.py
llamaapi/auth.py
llamaapi/cache.py
llamaapi/client.py
llamaapi/exceptions.py
llamaapi/middleware.py
llamaapi/openapi.py
llamaapi/schema.py
llamaapi/server.py
llamaapi_llamasearch-0.1.0.dist-info/licenses/LICENSE
llamaapi_llamasearch-0.1.0.dist-info/METADATA
llamaapi_llamasearch-0.1.0.dist-info/WHEEL
llamaapi_llamasearch-0.1.0.dist-info/top_level.txt
llamaapi_llamasearch-0.1.0.dist-info/RECORD
