Metadata-Version: 2.4
Name: llamaapi-llamasearch
Version: 0.1.0
Summary: A flexible API client and server utilities package
Home-page: https://llamasearch.ai
Author: LlamaSearch AI
Author-email: nikjois@llamasearch.ai
Project-URL: Bug Tracker, https://github.com/llamasearch/llamaapi/issues
Project-URL: Documentation, https://llamasearch.ai/docs/llamaapi
Project-URL: Source Code, https://github.com/llamasearch/llamaapi
Classifier: Programming Language :: Python :: 3
Classifier: Programming Language :: Python :: 3.8
Classifier: Programming Language :: Python :: 3.9
Classifier: Programming Language :: Python :: 3.10
Classifier: License :: OSI Approved :: MIT License
Classifier: Operating System :: OS Independent
Classifier: Development Status :: 4 - Beta
Classifier: Intended Audience :: Developers
Classifier: Topic :: Software Development :: Libraries :: Python Modules
Classifier: Topic :: Internet :: WWW/HTTP
Requires-Python: >=3.8
License-File: LICENSE
Requires-Dist: requests>=2.25.0
Requires-Dist: pydantic>=1.9.0
Requires-Dist: PyYAML>=6.0
Requires-Dist: redis>=4.3.4
Requires-Dist: ujson>=5.4.0
Requires-Dist: httpx>=0.23.0
Requires-Dist: marshmallow>=3.17.0
Requires-Dist: openapi-spec-validator>=0.4.0
Provides-Extra: dev
Requires-Dist: pytest>=7.0.0; extra == "dev"
Requires-Dist: pytest-cov>=3.0.0; extra == "dev"
Requires-Dist: black>=22.6.0; extra == "dev"
Requires-Dist: isort>=5.10.1; extra == "dev"
Requires-Dist: mypy>=0.971; extra == "dev"
Requires-Dist: flake8>=5.0.4; extra == "dev"
Provides-Extra: server
Requires-Dist: flask>=2.2.0; extra == "server"
Requires-Dist: fastapi>=0.85.0; extra == "server"
Requires-Dist: uvicorn>=0.18.3; extra == "server"
Provides-Extra: auth
Requires-Dist: pyjwt>=2.4.0; extra == "auth"
Requires-Dist: cryptography>=37.0.4; extra == "auth"
Provides-Extra: cache
Requires-Dist: cachetools>=5.2.0; extra == "cache"
Provides-Extra: docs
Requires-Dist: mkdocs>=1.4.0; extra == "docs"
Requires-Dist: mkdocs-material>=8.5.0; extra == "docs"
Requires-Dist: mkdocstrings>=0.19.0; extra == "docs"
Dynamic: author
Dynamic: author-email
Dynamic: classifier
Dynamic: description
Dynamic: description-content-type
Dynamic: home-page
Dynamic: license-file
Dynamic: project-url
Dynamic: provides-extra
Dynamic: requires-dist
Dynamic: requires-python
Dynamic: summary
